pyopencell/__init__.py
pyopencell/client.py
pyopencell/exceptions.py
pyopencell/helpers.py
pyopencell/resources/__init__.py
pyopencell/resources/access.py
pyopencell/resources/base_resource.py
pyopencell/resources/base_resource_list.py
pyopencell/resources/crm_account_hierarchy.py
pyopencell/resources/customer.py
pyopencell/resources/customer_account.py
pyopencell/resources/invoice.py
pyopencell/resources/invoice_list.py
pyopencell/resources/subscription.py
pyopencell/resources/subscription_list.py
pyopencell/responses/__init__.py
pyopencell/responses/action_status.py
pyopencell/responses/paged_response.py
pyopencell/responses/paging.py
pyopencell/responses/response.py
pyopencell-0.4.10.dist-info/LICENSE
pyopencell-0.4.10.dist-info/METADATA
pyopencell-0.4.10.dist-info/WHEEL
pyopencell-0.4.10.dist-info/top_level.txt
pyopencell-0.4.10.dist-info/RECORD
