Metadata-Version: 2.1
Name: pyopencell
Version: 0.4.10
Summary: Python wrapper for OpenCell (using REST API)
Home-page: https://gitlab.com/coopdevs/pyopencell
Author: Coopdevs
Author-email: info@coopdevs.org
Maintainer: Daniel Palomar, Antonio Barcia
License: UNKNOWN
Platform: UNKNOWN
Classifier: Development Status :: 3 - Alpha
Classifier: Operating System :: POSIX :: Linux
Classifier: Programming Language :: Python :: 2
Classifier: Programming Language :: Python :: 2.7
License-File: LICENSE
Requires-Dist: requests
